pydotfiles/__init__.py
pydotfiles/version.py
pydotfiles/api/__init__.py
pydotfiles/api/deprecated.py
pydotfiles/bin/pydotfiles
pydotfiles/common/__init__.py
pydotfiles/defaults/__init__.py
pydotfiles/defaults/primitives.py
pydotfiles/environments/__init__.py
pydotfiles/environments/plugins.py
pydotfiles/loading/__init__.py
pydotfiles/models/__init__.py
pydotfiles/models/constants.py
pydotfiles/models/dock.py
pydotfiles/models/enums.py
pydotfiles/models/exceptions.py
pydotfiles/models/primitives.py
pydotfiles/models/utils.py
pydotfiles/models/validator.py
pydotfiles/resources/__init__.py
pydotfiles/resources/schemas/__init__.py
pydotfiles/resources/schemas/alpha/__init__.py
pydotfiles/resources/schemas/alpha/common.json
pydotfiles/resources/schemas/alpha/core.json
pydotfiles/resources/schemas/alpha/default_settings.json
pydotfiles/resources/schemas/alpha/developer_environments.json
pydotfiles/resources/schemas/alpha/manifest.json
pydotfiles/utils/__init__.py
pydotfiles/utils/general.py
pydotfiles/utils/io.py
pydotfiles/v4/__init__.py
pydotfiles/v4/builder/__init__.py
pydotfiles/v4/builder/common.py
pydotfiles/v4/builder/environment.py
pydotfiles/v4/builder/io.py
pydotfiles/v4/builder/os.py
pydotfiles/v4/common/__init__.py
pydotfiles/v4/common/alpha/__init__.py
pydotfiles/v4/common/alpha/action.py
pydotfiles/v4/common/alpha/default_settings.py
pydotfiles/v4/common/alpha/environment.py
pydotfiles/v4/common/alpha/os.py
pydotfiles/v4/common/alpha/profiles.py
pydotfiles/v4/loader/__init__.py
pydotfiles/v4/logging/__init__.py
pydotfiles/v4/validator/__init__.py
pydotfiles/v4/validator/alpha/__init__.py
pydotfiles-4.2.8.data/scripts/pydotfiles
tests/__init__.py
tests/resources/__init__.py
tests/resources/validator/__init__.py
tests/resources/validator/alpha/__init__.py
tests/resources/validator/alpha/core/__init__.py
tests/resources/validator/alpha/core/invalid_schema_actions_invalid_action.json
tests/resources/validator/alpha/core/invalid_schema_actions_no_action.json
pydotfiles-4.2.8.dist-info/LICENSE
pydotfiles-4.2.8.dist-info/METADATA
pydotfiles-4.2.8.dist-info/WHEEL
pydotfiles-4.2.8.dist-info/top_level.txt
pydotfiles-4.2.8.dist-info/RECORD
