Metadata-Version: 2.1
Name: pydotfiles
Version: 4.2.8
Summary: Fast, easy, and automatic system configuration via a configuration file/repo
Home-page: https://github.com/JasonYao/pydotfiles
Author: Jason Yao
Author-email: Hello@JasonYao.com
License: GPLv3
Project-URL: Bug Reports, https://github.com/JasonYao/pydotfiles/issues
Project-URL: Source, https://github.com/JasonYao/pydotfiles
Platform: UNKNOWN
Classifier: Development Status :: 3 - Alpha
Classifier: Intended Audience :: Developers
Classifier: Topic :: System :: Systems Administration
Classifier: Programming Language :: Python :: 3 :: Only
Classifier: Programming Language :: Python :: 3.6
Classifier: Programming Language :: Python :: 3.7
Classifier: Operating System :: MacOS
Classifier: Operating System :: POSIX :: Linux
Classifier: Operating System :: Unix
Classifier: License :: OSI Approved :: GNU General Public License v3 (GPLv3)
Requires-Python: >=3.6
License-File: LICENSE
Requires-Dist: PyYAML (>=3.13)
Requires-Dist: jsonschema (>=2.6.0)
Requires-Dist: GitPython (>=2.1.11)
Requires-Dist: progressbar2 (>=3.38.0)
Requires-Dist: dataclasses ; python_version < "3.7"
Requires-Dist: importlib-resources ; python_version < "3.9"
